LICENSE
LICENSE.AGPL
MANIFEST.in
README.md
setup.py
in3/__init__.py
in3/client.py
in3/exception.py
in3/model.py
in3/transport.py
in3.egg-info/PKG-INFO
in3.egg-info/SOURCES.txt
in3.egg-info/dependency_links.txt
in3.egg-info/top_level.txt
in3/eth/__init__.py
in3/eth/account.py
in3/eth/api.py
in3/eth/contract.py
in3/eth/factory.py
in3/eth/model.py
in3/libin3/__init__.py
in3/libin3/enum.py
in3/libin3/rpc_api.py
in3/libin3/runtime.py
in3/libin3/storage.py
in3/libin3/transport.py
in3/libin3/shared/libin3.arm7.so
in3/libin3/shared/libin3.x64.dll
in3/libin3/shared/libin3.x64.dylib
in3/libin3/shared/libin3.x64.so
in3/libin3/shared/libin3.x86.so
tests/integrated/__init__.py
tests/integrated/mock/__init__.py
tests/integrated/mock/config.py
tests/integrated/mock/http.py
tests/integrated/mock/transport.py
tests/integrated/negative/__init__.py
tests/integrated/negative/client_test.py
tests/integrated/negative/eth_api_test.py
tests/integrated/positive/__init__.py
tests/integrated/positive/client_test.py
tests/integrated/positive/eth_account_test.py
tests/integrated/positive/eth_api_test.py
tests/integrated/positive/eth_contract_test.py