Metadata-Version: 2.1
Name: in3
Version: 3.2.2
Summary: Incubed client and provider for web3. Based on in3-c runtime.
Home-page: https://github.com/slockit/in3-c
Author: github.com/slockit/in3-c
Author-email: products@slock.it
License: UNKNOWN
Keywords: in3,c,arm,x86,x64,macos,windows,linux,blockchain,ethereum,bitcoin,ipfs
Platform: UNKNOWN
Classifier: Programming Language :: Python :: 3
Classifier: License :: OSI Approved :: GNU Affero General Public License v3 or later (AGPLv3+)
Classifier: Operating System :: OS Independent
Classifier: Natural Language :: English
Classifier: Intended Audience :: Science/Research
Classifier: Environment :: Console
Classifier: Development Status :: 4 - Beta
